wideresnet/__init__.py
wideresnet/wide_res_net.py
Wide_Residual_Network-1.1.dist-info/LICENSE
Wide_Residual_Network-1.1.dist-info/METADATA
Wide_Residual_Network-1.1.dist-info/WHEEL
Wide_Residual_Network-1.1.dist-info/top_level.txt
Wide_Residual_Network-1.1.dist-info/RECORD
